common/__init__.py
common/decorator.py
common/descriptor.py
common/metaclass.py
common/utils.py
common/variables.py
logs/__init__.py
logs/server_log_config.py
server/__init__.py
server/add_user.py
server/config_window.py
server/core.py
server/main_window.py
server/my_server_base.py
server/remove_user.py
server/stat_window.py
unitest/__init__.py
unitest/test_server.py
unitest/test_utils.py
message_server_unfun-0.8.7.dist-info/METADATA
message_server_unfun-0.8.7.dist-info/WHEEL
message_server_unfun-0.8.7.dist-info/top_level.txt
message_server_unfun-0.8.7.dist-info/RECORD
