Metadata-Version: 2.1
Name: message-server-unfun
Version: 0.8.7
Summary: message_server_unfun
Home-page: UNKNOWN
Author: Vladimir Gromov
Author-email: gromovvladimir@myrambler.ru
License: UNKNOWN
Platform: UNKNOWN
Requires-Dist: PyQt5
Requires-Dist: sqlalchemy
Requires-Dist: pycryptodome
Requires-Dist: pycryptodomex
